{
  "timestamp": "2026-03-05T16:35:06.692Z",
  "bottlenecks": [
    {
      "type": "sync_file_operations",
      "file": "./connectors/iflow-connector.js",
      "count": 2,
      "impact": "medium",
      "description": "发现 2 个同步文件操作",
      "recommendation": "使用异步文件操作提高并发性能"
    },
    {
      "type": "sync_file_operations",
      "file": "./server.js",
      "count": 1,
      "impact": "medium",
      "description": "发现 1 个同步文件操作",
      "recommendation": "使用异步文件操作提高并发性能"
    }
  ],
  "patterns": [
    {
      "type": "regex_compilation",
      "file": "utils/app-errors.js",
      "count": 25,
      "impact": "low",
      "description": "多个正则表达式可能被重复编译",
      "recommendation": "预编译正则表达式并缓存"
    },
    {
      "type": "regex_compilation",
      "file": "utils/batch-logger.js",
      "count": 37,
      "impact": "low",
      "description": "多个正则表达式可能被重复编译",
      "recommendation": "预编译正则表达式并缓存"
    },
    {
      "type": "regex_compilation",
      "file": "utils/cache-manager.js",
      "count": 71,
      "impact": "low",
      "description": "多个正则表达式可能被重复编译",
      "recommendation": "预编译正则表达式并缓存"
    },
    {
      "type": "regex_compilation",
      "file": "utils/config.js",
      "count": 48,
      "impact": "low",
      "description": "多个正则表达式可能被重复编译",
      "recommendation": "预编译正则表达式并缓存"
    },
    {
      "type": "regex_compilation",
      "file": "utils/deduplication-middleware.js",
      "count": 29,
      "impact": "low",
      "description": "多个正则表达式可能被重复编译",
      "recommendation": "预编译正则表达式并缓存"
    },
    {
      "type": "regex_compilation",
      "file": "utils/env-manager.js",
      "count": 32,
      "impact": "low",
      "description": "多个正则表达式可能被重复编译",
      "recommendation": "预编译正则表达式并缓存"
    },
    {
      "type": "regex_compilation",
      "file": "utils/error-handler.js",
      "count": 53,
      "impact": "low",
      "description": "多个正则表达式可能被重复编译",
      "recommendation": "预编译正则表达式并缓存"
    },
    {
      "type": "regex_compilation",
      "file": "utils/error-recovery.js",
      "count": 54,
      "impact": "low",
      "description": "多个正则表达式可能被重复编译",
      "recommendation": "预编译正则表达式并缓存"
    },
    {
      "type": "regex_compilation",
      "file": "utils/graceful-shutdown.js",
      "count": 25,
      "impact": "low",
      "description": "多个正则表达式可能被重复编译",
      "recommendation": "预编译正则表达式并缓存"
    },
    {
      "type": "regex_compilation",
      "file": "utils/health-check.js",
      "count": 35,
      "impact": "low",
      "description": "多个正则表达式可能被重复编译",
      "recommendation": "预编译正则表达式并缓存"
    },
    {
      "type": "regex_compilation",
      "file": "utils/health-enhanced.js",
      "count": 26,
      "impact": "low",
      "description": "多个正则表达式可能被重复编译",
      "recommendation": "预编译正则表达式并缓存"
    },
    {
      "type": "regex_compilation",
      "file": "utils/input-validator-middleware.js",
      "count": 55,
      "impact": "low",
      "description": "多个正则表达式可能被重复编译",
      "recommendation": "预编译正则表达式并缓存"
    },
    {
      "type": "regex_compilation",
      "file": "utils/input-validator.js",
      "count": 54,
      "impact": "low",
      "description": "多个正则表达式可能被重复编译",
      "recommendation": "预编译正则表达式并缓存"
    },
    {
      "type": "regex_compilation",
      "file": "utils/memory-cleaner.js",
      "count": 42,
      "impact": "low",
      "description": "多个正则表达式可能被重复编译",
      "recommendation": "预编译正则表达式并缓存"
    },
    {
      "type": "regex_compilation",
      "file": "utils/memory-monitor-enhanced.js",
      "count": 43,
      "impact": "low",
      "description": "多个正则表达式可能被重复编译",
      "recommendation": "预编译正则表达式并缓存"
    },
    {
      "type": "regex_compilation",
      "file": "utils/memory-monitor.js",
      "count": 33,
      "impact": "low",
      "description": "多个正则表达式可能被重复编译",
      "recommendation": "预编译正则表达式并缓存"
    },
    {
      "type": "regex_compilation",
      "file": "utils/message-formatter.js",
      "count": 9,
      "impact": "low",
      "description": "多个正则表达式可能被重复编译",
      "recommendation": "预编译正则表达式并缓存"
    },
    {
      "type": "regex_compilation",
      "file": "utils/middleware.js",
      "count": 59,
      "impact": "low",
      "description": "多个正则表达式可能被重复编译",
      "recommendation": "预编译正则表达式并缓存"
    },
    {
      "type": "regex_compilation",
      "file": "utils/notification-queue.js",
      "count": 48,
      "impact": "low",
      "description": "多个正则表达式可能被重复编译",
      "recommendation": "预编译正则表达式并缓存"
    },
    {
      "type": "regex_compilation",
      "file": "utils/performance-tracker.js",
      "count": 33,
      "impact": "low",
      "description": "多个正则表达式可能被重复编译",
      "recommendation": "预编译正则表达式并缓存"
    },
    {
      "type": "regex_compilation",
      "file": "utils/platform.js",
      "count": 6,
      "impact": "low",
      "description": "多个正则表达式可能被重复编译",
      "recommendation": "预编译正则表达式并缓存"
    },
    {
      "type": "regex_compilation",
      "file": "utils/rate-limit.js",
      "count": 19,
      "impact": "low",
      "description": "多个正则表达式可能被重复编译",
      "recommendation": "预编译正则表达式并缓存"
    },
    {
      "type": "regex_compilation",
      "file": "utils/rate-limiter-memory.js",
      "count": 11,
      "impact": "low",
      "description": "多个正则表达式可能被重复编译",
      "recommendation": "预编译正则表达式并缓存"
    },
    {
      "type": "regex_compilation",
      "file": "utils/rate-limiter.js",
      "count": 11,
      "impact": "low",
      "description": "多个正则表达式可能被重复编译",
      "recommendation": "预编译正则表达式并缓存"
    },
    {
      "type": "regex_compilation",
      "file": "utils/request-deduplication.js",
      "count": 18,
      "impact": "low",
      "description": "多个正则表达式可能被重复编译",
      "recommendation": "预编译正则表达式并缓存"
    },
    {
      "type": "regex_compilation",
      "file": "utils/request-stats.js",
      "count": 26,
      "impact": "low",
      "description": "多个正则表达式可能被重复编译",
      "recommendation": "预编译正则表达式并缓存"
    },
    {
      "type": "regex_compilation",
      "file": "utils/response-cache.js",
      "count": 53,
      "impact": "low",
      "description": "多个正则表达式可能被重复编译",
      "recommendation": "预编译正则表达式并缓存"
    },
    {
      "type": "regex_compilation",
      "file": "utils/response-formatter.js",
      "count": 25,
      "impact": "low",
      "description": "多个正则表达式可能被重复编译",
      "recommendation": "预编译正则表达式并缓存"
    },
    {
      "type": "regex_compilation",
      "file": "utils/response-optimizer.js",
      "count": 37,
      "impact": "low",
      "description": "多个正则表达式可能被重复编译",
      "recommendation": "预编译正则表达式并缓存"
    },
    {
      "type": "regex_compilation",
      "file": "utils/retry-helper.js",
      "count": 30,
      "impact": "low",
      "description": "多个正则表达式可能被重复编译",
      "recommendation": "预编译正则表达式并缓存"
    },
    {
      "type": "regex_compilation",
      "file": "utils/sanitizer.js",
      "count": 42,
      "impact": "low",
      "description": "多个正则表达式可能被重复编译",
      "recommendation": "预编译正则表达式并缓存"
    },
    {
      "type": "regex_compilation",
      "file": "utils/security-enhancer.js",
      "count": 83,
      "impact": "low",
      "description": "多个正则表达式可能被重复编译",
      "recommendation": "预编译正则表达式并缓存"
    },
    {
      "type": "regex_compilation",
      "file": "utils/startup-check.js",
      "count": 28,
      "impact": "low",
      "description": "多个正则表达式可能被重复编译",
      "recommendation": "预编译正则表达式并缓存"
    },
    {
      "type": "regex_compilation",
      "file": "utils/string-helper.js",
      "count": 8,
      "impact": "low",
      "description": "多个正则表达式可能被重复编译",
      "recommendation": "预编译正则表达式并缓存"
    },
    {
      "type": "regex_compilation",
      "file": "utils/task-queue.js",
      "count": 28,
      "impact": "low",
      "description": "多个正则表达式可能被重复编译",
      "recommendation": "预编译正则表达式并缓存"
    },
    {
      "type": "regex_compilation",
      "file": "utils/validators.js",
      "count": 51,
      "impact": "low",
      "description": "多个正则表达式可能被重复编译",
      "recommendation": "预编译正则表达式并缓存"
    },
    {
      "type": "loop_computation",
      "file": "./connectors/iflow-connector.js",
      "count": 2,
      "impact": "medium",
      "description": "循环中可能存在重复计算",
      "recommendation": "将不变的计算移出循环"
    },
    {
      "type": "loop_computation",
      "file": "./integrations/dingtalk.js",
      "count": 1,
      "impact": "medium",
      "description": "循环中可能存在重复计算",
      "recommendation": "将不变的计算移出循环"
    },
    {
      "type": "cache_opportunity",
      "file": "utils/app-errors.js",
      "pattern": "正则表达式",
      "count": 25,
      "impact": "low",
      "description": "正则表达式可以预编译",
      "recommendation": "考虑使用缓存减少重复计算"
    },
    {
      "type": "cache_opportunity",
      "file": "utils/batch-logger.js",
      "pattern": "正则表达式",
      "count": 37,
      "impact": "low",
      "description": "正则表达式可以预编译",
      "recommendation": "考虑使用缓存减少重复计算"
    },
    {
      "type": "cache_opportunity",
      "file": "utils/cache-manager.js",
      "pattern": "正则表达式",
      "count": 71,
      "impact": "low",
      "description": "正则表达式可以预编译",
      "recommendation": "考虑使用缓存减少重复计算"
    },
    {
      "type": "cache_opportunity",
      "file": "utils/config.js",
      "pattern": "正则表达式",
      "count": 48,
      "impact": "low",
      "description": "正则表达式可以预编译",
      "recommendation": "考虑使用缓存减少重复计算"
    },
    {
      "type": "cache_opportunity",
      "file": "utils/deduplication-middleware.js",
      "pattern": "正则表达式",
      "count": 29,
      "impact": "low",
      "description": "正则表达式可以预编译",
      "recommendation": "考虑使用缓存减少重复计算"
    },
    {
      "type": "cache_opportunity",
      "file": "utils/env-manager.js",
      "pattern": "正则表达式",
      "count": 32,
      "impact": "low",
      "description": "正则表达式可以预编译",
      "recommendation": "考虑使用缓存减少重复计算"
    },
    {
      "type": "cache_opportunity",
      "file": "utils/error-handler.js",
      "pattern": "正则表达式",
      "count": 55,
      "impact": "low",
      "description": "正则表达式可以预编译",
      "recommendation": "考虑使用缓存减少重复计算"
    },
    {
      "type": "cache_opportunity",
      "file": "utils/error-recovery.js",
      "pattern": "正则表达式",
      "count": 56,
      "impact": "low",
      "description": "正则表达式可以预编译",
      "recommendation": "考虑使用缓存减少重复计算"
    },
    {
      "type": "cache_opportunity",
      "file": "utils/graceful-shutdown.js",
      "pattern": "正则表达式",
      "count": 25,
      "impact": "low",
      "description": "正则表达式可以预编译",
      "recommendation": "考虑使用缓存减少重复计算"
    },
    {
      "type": "cache_opportunity",
      "file": "utils/health-check.js",
      "pattern": "正则表达式",
      "count": 37,
      "impact": "low",
      "description": "正则表达式可以预编译",
      "recommendation": "考虑使用缓存减少重复计算"
    },
    {
      "type": "cache_opportunity",
      "file": "utils/health-enhanced.js",
      "pattern": "正则表达式",
      "count": 28,
      "impact": "low",
      "description": "正则表达式可以预编译",
      "recommendation": "考虑使用缓存减少重复计算"
    },
    {
      "type": "cache_opportunity",
      "file": "utils/input-validator-middleware.js",
      "pattern": "正则表达式",
      "count": 76,
      "impact": "low",
      "description": "正则表达式可以预编译",
      "recommendation": "考虑使用缓存减少重复计算"
    },
    {
      "type": "cache_opportunity",
      "file": "utils/input-validator.js",
      "pattern": "正则表达式",
      "count": 59,
      "impact": "low",
      "description": "正则表达式可以预编译",
      "recommendation": "考虑使用缓存减少重复计算"
    },
    {
      "type": "cache_opportunity",
      "file": "utils/memory-cleaner.js",
      "pattern": "正则表达式",
      "count": 45,
      "impact": "low",
      "description": "正则表达式可以预编译",
      "recommendation": "考虑使用缓存减少重复计算"
    },
    {
      "type": "cache_opportunity",
      "file": "utils/memory-monitor-enhanced.js",
      "pattern": "正则表达式",
      "count": 43,
      "impact": "low",
      "description": "正则表达式可以预编译",
      "recommendation": "考虑使用缓存减少重复计算"
    },
    {
      "type": "cache_opportunity",
      "file": "utils/memory-monitor.js",
      "pattern": "正则表达式",
      "count": 33,
      "impact": "low",
      "description": "正则表达式可以预编译",
      "recommendation": "考虑使用缓存减少重复计算"
    },
    {
      "type": "cache_opportunity",
      "file": "utils/message-formatter.js",
      "pattern": "正则表达式",
      "count": 9,
      "impact": "low",
      "description": "正则表达式可以预编译",
      "recommendation": "考虑使用缓存减少重复计算"
    },
    {
      "type": "cache_opportunity",
      "file": "utils/middleware.js",
      "pattern": "正则表达式",
      "count": 59,
      "impact": "low",
      "description": "正则表达式可以预编译",
      "recommendation": "考虑使用缓存减少重复计算"
    },
    {
      "type": "cache_opportunity",
      "file": "utils/notification-queue.js",
      "pattern": "正则表达式",
      "count": 48,
      "impact": "low",
      "description": "正则表达式可以预编译",
      "recommendation": "考虑使用缓存减少重复计算"
    },
    {
      "type": "cache_opportunity",
      "file": "utils/performance-tracker.js",
      "pattern": "正则表达式",
      "count": 33,
      "impact": "low",
      "description": "正则表达式可以预编译",
      "recommendation": "考虑使用缓存减少重复计算"
    },
    {
      "type": "cache_opportunity",
      "file": "utils/platform.js",
      "pattern": "正则表达式",
      "count": 6,
      "impact": "low",
      "description": "正则表达式可以预编译",
      "recommendation": "考虑使用缓存减少重复计算"
    },
    {
      "type": "cache_opportunity",
      "file": "utils/rate-limit.js",
      "pattern": "正则表达式",
      "count": 19,
      "impact": "low",
      "description": "正则表达式可以预编译",
      "recommendation": "考虑使用缓存减少重复计算"
    },
    {
      "type": "cache_opportunity",
      "file": "utils/rate-limiter-memory.js",
      "pattern": "正则表达式",
      "count": 11,
      "impact": "low",
      "description": "正则表达式可以预编译",
      "recommendation": "考虑使用缓存减少重复计算"
    },
    {
      "type": "cache_opportunity",
      "file": "utils/rate-limiter.js",
      "pattern": "正则表达式",
      "count": 11,
      "impact": "low",
      "description": "正则表达式可以预编译",
      "recommendation": "考虑使用缓存减少重复计算"
    },
    {
      "type": "cache_opportunity",
      "file": "utils/request-deduplication.js",
      "pattern": "正则表达式",
      "count": 18,
      "impact": "low",
      "description": "正则表达式可以预编译",
      "recommendation": "考虑使用缓存减少重复计算"
    },
    {
      "type": "cache_opportunity",
      "file": "utils/request-stats.js",
      "pattern": "正则表达式",
      "count": 26,
      "impact": "low",
      "description": "正则表达式可以预编译",
      "recommendation": "考虑使用缓存减少重复计算"
    },
    {
      "type": "cache_opportunity",
      "file": "utils/response-cache.js",
      "pattern": "正则表达式",
      "count": 53,
      "impact": "low",
      "description": "正则表达式可以预编译",
      "recommendation": "考虑使用缓存减少重复计算"
    },
    {
      "type": "cache_opportunity",
      "file": "utils/response-formatter.js",
      "pattern": "正则表达式",
      "count": 25,
      "impact": "low",
      "description": "正则表达式可以预编译",
      "recommendation": "考虑使用缓存减少重复计算"
    },
    {
      "type": "cache_opportunity",
      "file": "utils/response-optimizer.js",
      "pattern": "正则表达式",
      "count": 37,
      "impact": "low",
      "description": "正则表达式可以预编译",
      "recommendation": "考虑使用缓存减少重复计算"
    },
    {
      "type": "cache_opportunity",
      "file": "utils/retry-helper.js",
      "pattern": "正则表达式",
      "count": 30,
      "impact": "low",
      "description": "正则表达式可以预编译",
      "recommendation": "考虑使用缓存减少重复计算"
    },
    {
      "type": "cache_opportunity",
      "file": "utils/sanitizer.js",
      "pattern": "正则表达式",
      "count": 58,
      "impact": "low",
      "description": "正则表达式可以预编译",
      "recommendation": "考虑使用缓存减少重复计算"
    },
    {
      "type": "cache_opportunity",
      "file": "utils/security-enhancer.js",
      "pattern": "正则表达式",
      "count": 99,
      "impact": "low",
      "description": "正则表达式可以预编译",
      "recommendation": "考虑使用缓存减少重复计算"
    },
    {
      "type": "cache_opportunity",
      "file": "utils/startup-check.js",
      "pattern": "正则表达式",
      "count": 28,
      "impact": "low",
      "description": "正则表达式可以预编译",
      "recommendation": "考虑使用缓存减少重复计算"
    },
    {
      "type": "cache_opportunity",
      "file": "utils/string-helper.js",
      "pattern": "正则表达式",
      "count": 8,
      "impact": "low",
      "description": "正则表达式可以预编译",
      "recommendation": "考虑使用缓存减少重复计算"
    },
    {
      "type": "cache_opportunity",
      "file": "utils/task-queue.js",
      "pattern": "正则表达式",
      "count": 28,
      "impact": "low",
      "description": "正则表达式可以预编译",
      "recommendation": "考虑使用缓存减少重复计算"
    },
    {
      "type": "cache_opportunity",
      "file": "utils/validators.js",
      "pattern": "正则表达式",
      "count": 58,
      "impact": "low",
      "description": "正则表达式可以预编译",
      "recommendation": "考虑使用缓存减少重复计算"
    }
  ],
  "recommendations": [
    {
      "priority": "medium",
      "category": "sync_file_operations",
      "title": "替换同步文件操作",
      "description": "发现 2 个同步文件操作",
      "recommendation": "使用异步文件操作提高并发性能",
      "file": "./connectors/iflow-connector.js",
      "estimatedImpact": "moderate"
    },
    {
      "priority": "medium",
      "category": "sync_file_operations",
      "title": "替换同步文件操作",
      "description": "发现 1 个同步文件操作",
      "recommendation": "使用异步文件操作提高并发性能",
      "file": "./server.js",
      "estimatedImpact": "moderate"
    },
    {
      "priority": "low",
      "category": "pattern_optimization",
      "title": "优化 regex_compilation 模式",
      "description": "在 36 个文件中发现此模式",
      "recommendation": "预编译正则表达式并缓存",
      "files": [
        "utils/app-errors.js",
        "utils/batch-logger.js",
        "utils/cache-manager.js",
        "utils/config.js",
        "utils/deduplication-middleware.js",
        "utils/env-manager.js",
        "utils/error-handler.js",
        "utils/error-recovery.js",
        "utils/graceful-shutdown.js",
        "utils/health-check.js",
        "utils/health-enhanced.js",
        "utils/input-validator-middleware.js",
        "utils/input-validator.js",
        "utils/memory-cleaner.js",
        "utils/memory-monitor-enhanced.js",
        "utils/memory-monitor.js",
        "utils/message-formatter.js",
        "utils/middleware.js",
        "utils/notification-queue.js",
        "utils/performance-tracker.js",
        "utils/platform.js",
        "utils/rate-limit.js",
        "utils/rate-limiter-memory.js",
        "utils/rate-limiter.js",
        "utils/request-deduplication.js",
        "utils/request-stats.js",
        "utils/response-cache.js",
        "utils/response-formatter.js",
        "utils/response-optimizer.js",
        "utils/retry-helper.js",
        "utils/sanitizer.js",
        "utils/security-enhancer.js",
        "utils/startup-check.js",
        "utils/string-helper.js",
        "utils/task-queue.js",
        "utils/validators.js"
      ],
      "estimatedImpact": "minor"
    },
    {
      "priority": "low",
      "category": "pattern_optimization",
      "title": "优化 cache_opportunity 模式",
      "description": "在 36 个文件中发现此模式",
      "recommendation": "考虑使用缓存减少重复计算",
      "files": [
        "utils/app-errors.js",
        "utils/batch-logger.js",
        "utils/cache-manager.js",
        "utils/config.js",
        "utils/deduplication-middleware.js",
        "utils/env-manager.js",
        "utils/error-handler.js",
        "utils/error-recovery.js",
        "utils/graceful-shutdown.js",
        "utils/health-check.js",
        "utils/health-enhanced.js",
        "utils/input-validator-middleware.js",
        "utils/input-validator.js",
        "utils/memory-cleaner.js",
        "utils/memory-monitor-enhanced.js",
        "utils/memory-monitor.js",
        "utils/message-formatter.js",
        "utils/middleware.js",
        "utils/notification-queue.js",
        "utils/performance-tracker.js",
        "utils/platform.js",
        "utils/rate-limit.js",
        "utils/rate-limiter-memory.js",
        "utils/rate-limiter.js",
        "utils/request-deduplication.js",
        "utils/request-stats.js",
        "utils/response-cache.js",
        "utils/response-formatter.js",
        "utils/response-optimizer.js",
        "utils/retry-helper.js",
        "utils/sanitizer.js",
        "utils/security-enhancer.js",
        "utils/startup-check.js",
        "utils/string-helper.js",
        "utils/task-queue.js",
        "utils/validators.js"
      ],
      "estimatedImpact": "minor"
    }
  ],
  "summary": {
    "totalBottlenecks": 2,
    "highImpactBottlenecks": 0,
    "mediumImpactBottlenecks": 2,
    "optimizationPatterns": 74,
    "totalRecommendations": 4,
    "criticalIssues": 0,
    "performanceHealth": "poor"
  },
  "generatedAt": "2026/3/6 00:35:06"
}